level_4/better_processor/rtl/ALU.sv
module ALU (
    input wire [15:0] in_a,
    input wire [15:0] in_b,
    input wire [2:0] select,
    output reg [15:0] alu_out
);
    localparam add = 0, sub = 1, and_op = 2, or_op = 3, xor_op = 4, shl = 5, shr = 6, cmp = 7;
    always @(*) begin
        alu_out = 16'b0;
        case(select)
            add: alu_out = in_a + in_b;
            sub: alu_out = in_a - in_b;
            and_op: alu_out = in_a & in_b;
            or_op: alu_out = in_a | in_b;
            xor_op: alu_out = in_a ^ in_b;
            shl: alu_out = in_a << in_b;
            shr: alu_out = in_a >> in_b;
            cmp: alu_out = (in_a > in_b) ? 1: (in_a < in_b) ? 2: 0;
        endcase
    end
endmodule

level_4/better_processor/trace.vcd
$version Generated by VerilatedVcd $end
$timescale 1ps $end
 $scope module TOP $end
  $var wire 16 # in_a [15:0] $end
  $var wire 16 $ in_b [15:0] $end
  $var wire 3 % select [2:0] $end
  $var wire 16 & alu_out [15:0] $end
  $scope module ALU $end
   $var wire 16 # in_a [15:0] $end
   $var wire 16 $ in_b [15:0] $end
   $var wire 3 % select [2:0] $end
   $var wire 16 & alu_out [15:0] $end
   $var wire 32 ' add [31:0] $end
   $var wire 32 ( sub [31:0] $end
   $var wire 32 ) and_op [31:0] $end
   $var wire 32 * or_op [31:0] $end
   $var wire 32 + xor_op [31:0] $end
   $var wire 32 , shl [31:0] $end
   $var wire 32 - shr [31:0] $end
   $var wire 32 . cmp [31:0] $end
  $upscope $end
 $upscope $end
$enddefinitions $end


#0
b0000000000000000 #
b1000011010100000 $
b000 %
b1000011010100000 &
b00000000000000000000000000000000 '
b00000000000000000000000000000001 (
b00000000000000000000000000000010 )
b00000000000000000000000000000011 *
b00000000000000000000000000000100 +
b00000000000000000000000000000101 ,
b00000000000000000000000000000110 -
b00000000000000000000000000000111 .
#1
b001 %
b0111100101100000 &
#2
b010 %
b0000000000000000 &
#3
b011 %
b1000011010100000 &
#4
b100 %
#5
b101 %
b0000000000000000 &
#6
b110 %
#7
b111 %
b0000000000000010 &
#8
b000 %
b1000011010100000 &
#9
b001 %
b0111100101100000 &
#10
b010 %
b0000000000000000 &
#11
b011 %
b1000011010100000 &
#12
b100 %
#13
b101 %
b0000000000000000 &
#14
b110 %
#15
b111 %
b0000000000000010 &
#16
b000 %
b1000011010100000 &
#17
b001 %
b0111100101100000 &
#18
b010 %
b0000000000000000 &
#19
b011 %
b1000011010100000 &
#20
b100 %
#21
b101 %
b0000000000000000 &
#22
b110 %
#23
b111 %
b0000000000000010 &
#24
b000 %
b1000011010100000 &
#25
b001 %
b0111100101100000 &
#26
b010 %
b0000000000000000 &
#27
b011 %
b1000011010100000 &
#28
b100 %
#29
b101 %
b0000000000000000 &
#30
b110 %
#31
b111 %
b0000000000000010 &
#32
b000 %
b1000011010100000 &
#33
b001 %
b0111100101100000 &
#34
b010 %
b0000000000000000 &
#35
b011 %
b1000011010100000 &
#36
b100 %
#37
b101 %
b0000000000000000 &
#38
b110 %
#39
b111 %
b0000000000000010 &
#40
b000 %
b1000011010100000 &
#41
b001 %
b0111100101100000 &
#42
b010 %
b0000000000000000 &
#43
b011 %
b1000011010100000 &
#44
b100 %
#45
b101 %
b0000000000000000 &
#46
b110 %
#47
b111 %
b0000000000000010 &
#48
b000 %
b1000011010100000 &
#49
b001 %
b0111100101100000 &
#50
b010 %
b0000000000000000 &
#51
b011 %
b1000011010100000 &
#52
b100 %
#53
b101 %
b0000000000000000 &
#54
b110 %
#55
b111 %
b0000000000000010 &
#56
b000 %
b1000011010100000 &
#57
b001 %
b0111100101100000 &
#58
b010 %
b0000000000000000 &
#59
b011 %
b1000011010100000 &
#60
b100 %
#61
b101 %
b0000000000000000 &
#62
b110 %
#63
b111 %
b0000000000000010 &
#64
b000 %
b1000011010100000 &
#65
b001 %
b0111100101100000 &
#66
b010 %
b0000000000000000 &
#67
b011 %
b1000011010100000 &
#68
b100 %
#69
b101 %
b0000000000000000 &
#70
b110 %
#71
b111 %
b0000000000000010 &
#72
b000 %
b1000011010100000 &
#73
b001 %
b0111100101100000 &
#74
b010 %
b0000000000000000 &
#75
b011 %
b1000011010100000 &
#76
b100 %
#77
b101 %
b0000000000000000 &
#78
b110 %
#79
b111 %
b0000000000000010 &
#80
b000 %
b1000011010100000 &
#81
b001 %
b0111100101100000 &
#82
b010 %
b0000000000000000 &
#83
b011 %
b1000011010100000 &
#84
b100 %
#85
b101 %
b0000000000000000 &
#86
b110 %
#87
b111 %
b0000000000000010 &
#88
b000 %
b1000011010100000 &
#89
b001 %
b0111100101100000 &
#90
b010 %
b0000000000000000 &
#91
b011 %
b1000011010100000 &
#92
b100 %
#93
b101 %
b0000000000000000 &
#94
b110 %
#95
b111 %
b0000000000000010 &
#96
b000 %
b1000011010100000 &
#97
b001 %
b0111100101100000 &
#98
b010 %
b0000000000000000 &
#99
b011 %
b1000011010100000 &
#100
b100 %
#101
b101 %
b0000000000000000 &
#102
b110 %
#103
b111 %
b0000000000000010 &
#104
b000 %
b1000011010100000 &
#105
b001 %
b0111100101100000 &
#106
b010 %
b0000000000000000 &
#107
b011 %
b1000011010100000 &
#108
b100 %
#109
b101 %
b0000000000000000 &
#110
b110 %
#111
b111 %
b0000000000000010 &
#112
b000 %
b1000011010100000 &
#113
b001 %
b0111100101100000 &
#114
b010 %
b0000000000000000 &
#115
b011 %
b1000011010100000 &
#116
b100 %
#117
b101 %
b0000000000000000 &
#118
b110 %
#119
b111 %
b0000000000000010 &
#120
b000 %
b1000011010100000 &
#121
b001 %
b0111100101100000 &
#122
b010 %
b0000000000000000 &
#123
b011 %
b1000011010100000 &
#124
b100 %
#125
b101 %
b0000000000000000 &
#126
b110 %
#127
b111 %
b0000000000000010 &
#128
b000 %
b1000011010100000 &
#129
b001 %
b0111100101100000 &
#130
b010 %
b0000000000000000 &
#131
b011 %
b1000011010100000 &
#132
b100 %
#133
b101 %
b0000000000000000 &
#134
b110 %
#135
b111 %
b0000000000000010 &
#136
b000 %
b1000011010100000 &
#137
b001 %
b0111100101100000 &
#138
b010 %
b0000000000000000 &
#139
b011 %
b1000011010100000 &
#140
b100 %
#141
b101 %
b0000000000000000 &
#142
b110 %
#143
b111 %
b0000000000000010 &
#144
b000 %
b1000011010100000 &
#145
b001 %
b0111100101100000 &
#146
b010 %
b0000000000000000 &
#147
b011 %
b1000011010100000 &
#148
b100 %
#149
b101 %
b0000000000000000 &
#150
b110 %
#151
b111 %
b0000000000000010 &
#152
b000 %
b1000011010100000 &
#153
b001 %
b0111100101100000 &
#154
b010 %
b0000000000000000 &
#155
b011 %
b1000011010100000 &
#156
b100 %
#157
b101 %
b0000000000000000 &
#158
b110 %
#159
b111 %
b0000000000000010 &
#160
b000 %
b1000011010100000 &
#161
b001 %
b0111100101100000 &
#162
b010 %
b0000000000000000 &
#163
b011 %
b1000011010100000 &
#164
b100 %
#165
b101 %
b0000000000000000 &
#166
b110 %
#167
b111 %
b0000000000000010 &
#168
b000 %
b1000011010100000 &
#169
b001 %
b0111100101100000 &
#170
b010 %
b0000000000000000 &
#171
b011 %
b1000011010100000 &
#172
b100 %
#173
b101 %
b0000000000000000 &
#174
b110 %
#175
b111 %
b0000000000000010 &
#176
b000 %
b1000011010100000 &
#177
b001 %
b0111100101100000 &
#178
b010 %
b0000000000000000 &
#179
b011 %
b1000011010100000 &
#180
b100 %
#181
b101 %
b0000000000000000 &
#182
b110 %
#183
b111 %
b0000000000000010 &
#184
b000 %
b1000011010100000 &
#185
b001 %
b0111100101100000 &
#186
b010 %
b0000000000000000 &
#187
b011 %
b1000011010100000 &
#188
b100 %
#189
b101 %
b0000000000000000 &
#190
b110 %
#191
b111 %
b0000000000000010 &
#192
b000 %
b1000011010100000 &
#193
b001 %
b0111100101100000 &
#194
b010 %
b0000000000000000 &
#195
b011 %
b1000011010100000 &
#196
b100 %
#197
b101 %
b0000000000000000 &
#198
b110 %
#199
b111 %
b0000000000000010 &
#200
b000 %
b1000011010100000 &
#201
b001 %
b0111100101100000 &
#202
b010 %
b0000000000000000 &
#203
b011 %
b1000011010100000 &
#204
b100 %
#205
b101 %
b0000000000000000 &
#206
b110 %
#207
b111 %
b0000000000000010 &
#208
b000 %
b1000011010100000 &
#209
b001 %
b0111100101100000 &
#210
b010 %
b0000000000000000 &
#211
b011 %
b1000011010100000 &
#212
b100 %
#213
b101 %
b0000000000000000 &
#214
b110 %
#215
b111 %
b0000000000000010 &
#216
b000 %
b1000011010100000 &
#217
b001 %
b0111100101100000 &
#218
b010 %
b0000000000000000 &
#219
b011 %
b1000011010100000 &
#220
b100 %
#221
b101 %
b0000000000000000 &
#222
b110 %
#223
b111 %
b0000000000000010 &
#224
b000 %
b1000011010100000 &
#225
b001 %
b0111100101100000 &
#226
b010 %
b0000000000000000 &
#227
b011 %
b1000011010100000 &
#228
b100 %
#229
b101 %
b0000000000000000 &
#230
b110 %
#231
b111 %
b0000000000000010 &
#232
b000 %
b1000011010100000 &
#233
b001 %
b0111100101100000 &
#234
b010 %
b0000000000000000 &
#235
b011 %
b1000011010100000 &
#236
b100 %
#237
b101 %
b0000000000000000 &
#238
b110 %
#239
b111 %
b0000000000000010 &
#240
b000 %
b1000011010100000 &
#241
b001 %
b0111100101100000 &
#242
b010 %
b0000000000000000 &
#243
b011 %
b1000011010100000 &
#244
b100 %
#245
b101 %
b0000000000000000 &
#246
b110 %
#247
b111 %
b0000000000000010 &
#248
b000 %
b1000011010100000 &
#249
b001 %
b0111100101100000 &
#250
b010 %
b0000000000000000 &
#251
b011 %
b1000011010100000 &
#252
b100 %
#253
b101 %
b0000000000000000 &
#254
b110 %
#255
b111 %
b0000000000000010 &
#256
b000 %
b1000011010100000 &
#257
b001 %
b0111100101100000 &
#258
b010 %
b0000000000000000 &
#259
b011 %
b1000011010100000 &
#260
b100 %
#261
b101 %
b0000000000000000 &
#262
b110 %
#263
b111 %
b0000000000000010 &
#264
b000 %
b1000011010100000 &
#265
b001 %
b0111100101100000 &
#266
b010 %
b0000000000000000 &
#267
b011 %
b1000011010100000 &
#268
b100 %
#269
b101 %
b0000000000000000 &
#270
b110 %
#271
b111 %
b0000000000000010 &
#272
b000 %
b1000011010100000 &
#273
b001 %
b0111100101100000 &
#274
b010 %
b0000000000000000 &
#275
b011 %
b1000011010100000 &
#276
b100 %
#277
b101 %
b0000000000000000 &
#278
b110 %
#279
b111 %
b0000000000000010 &
#280
b000 %
b1000011010100000 &
#281
b001 %
b0111100101100000 &
#282
b010 %
b0000000000000000 &
#283
b011 %
b1000011010100000 &
#284
b100 %
#285
b101 %
b0000000000000000 &
#286
b110 %
#287
b111 %
b0000000000000010 &
#288
b000 %
b1000011010100000 &
#289
b001 %
b0111100101100000 &
#290
b010 %
b0000000000000000 &
#291
b011 %
b1000011010100000 &
#292
b100 %
#293
b101 %
b0000000000000000 &
#294
b110 %
#295
b111 %
b0000000000000010 &
#296
b000 %
b1000011010100000 &
#297
b001 %
b0111100101100000 &
#298
b010 %
b0000000000000000 &
#299
b011 %
b1000011010100000 &
#300
b100 %
#301
b101 %
b0000000000000000 &
#302
b110 %
#303
b111 %
b0000000000000010 &
#304
b000 %
b1000011010100000 &
#305
b001 %
b0111100101100000 &
#306
b010 %
b0000000000000000 &
#307
b011 %
b1000011010100000 &
#308
b100 %
#309
b101 %
b0000000000000000 &
#310
b110 %
#311
b111 %
b0000000000000010 &
#312
b000 %
b1000011010100000 &
#313
b001 %
b0111100101100000 &
#314
b010 %
b0000000000000000 &
#315
b011 %
b1000011010100000 &
#316
b100 %
#317
b101 %
b0000000000000000 &
#318
b110 %
#319
b111 %
b0000000000000010 &
#320
b000 %
b1000011010100000 &
#321
b001 %
b0111100101100000 &
#322
b010 %
b0000000000000000 &
#323
b011 %
b1000011010100000 &
#324
b100 %
#325
b101 %
b0000000000000000 &
#326
b110 %
#327
b111 %
b0000000000000010 &
#328
b000 %
b1000011010100000 &
#329
b001 %
b0111100101100000 &
#330
b010 %
b0000000000000000 &
#331
b011 %
b1000011010100000 &
#332
b100 %
#333
b101 %
b0000000000000000 &
#334
b110 %
#335
b111 %
b0000000000000010 &
#336
b000 %
b1000011010100000 &
#337
b001 %
b0111100101100000 &
#338
b010 %
b0000000000000000 &
#339
b011 %
b1000011010100000 &
#340
b100 %
#341
b101 %
b0000000000000000 &
#342
b110 %
#343
b111 %
b0000000000000010 &
#344
b000 %
b1000011010100000 &
#345
b001 %
b0111100101100000 &
#346
b010 %
b0000000000000000 &
#347
b011 %
b1000011010100000 &
#348
b100 %
#349
b101 %
b0000000000000000 &
#350
b110 %
#351
b111 %
b0000000000000010 &
#352
b000 %
b1000011010100000 &
#353
b001 %
b0111100101100000 &
#354
b010 %
b0000000000000000 &
#355
b011 %
b1000011010100000 &
#356
b100 %
#357
b101 %
b0000000000000000 &
#358
b110 %
#359
b111 %
b0000000000000010 &
#360
b000 %
b1000011010100000 &
#361
b001 %
b0111100101100000 &
#362
b010 %
b0000000000000000 &
#363
b011 %
b1000011010100000 &
#364
b100 %
#365
b101 %
b0000000000000000 &
#366
b110 %
#367
b111 %
b0000000000000010 &
#368
b000 %
b1000011010100000 &
#369
b001 %
b0111100101100000 &
#370
b010 %
b0000000000000000 &
#371
b011 %
b1000011010100000 &
#372
b100 %
#373
b101 %
b0000000000000000 &
#374
b110 %
#375
b111 %
b0000000000000010 &
#376
b000 %
b1000011010100000 &
#377
b001 %
b0111100101100000 &
#378
b010 %
b0000000000000000 &
#379
b011 %
b1000011010100000 &
#380
b100 %
#381
b101 %
b0000000000000000 &
#382
b110 %
#383
b111 %
b0000000000000010 &
#384
b000 %
b1000011010100000 &
#385
b001 %
b0111100101100000 &
#386
b010 %
b0000000000000000 &
#387
b011 %
b1000011010100000 &
#388
b100 %
#389
b101 %
b0000000000000000 &
#390
b110 %
#391
b111 %
b0000000000000010 &
#392
b000 %
b1000011010100000 &
#393
b001 %
b0111100101100000 &
#394
b010 %
b0000000000000000 &
#395
b011 %
b1000011010100000 &
#396
b100 %
#397
b101 %
b0000000000000000 &
#398
b110 %
#399
b111 %
b0000000000000010 &
#400
b000 %
b1000011010100000 &
#401
b001 %
b0111100101100000 &
#402
b010 %
b0000000000000000 &
#403
b011 %
b1000011010100000 &
#404
b100 %
#405
b101 %
b0000000000000000 &
#406
b110 %
#407
b111 %
b0000000000000010 &
#408
b000 %
b1000011010100000 &
#409
b001 %
b0111100101100000 &
#410
b010 %
b0000000000000000 &
#411
b011 %
b1000011010100000 &
#412
b100 %
#413
b101 %
b0000000000000000 &
#414
b110 %
#415
b111 %
b0000000000000010 &
#416
b000 %
b1000011010100000 &
#417
b001 %
b0111100101100000 &
#418
b010 %
b0000000000000000 &
#419
b011 %
b1000011010100000 &
#420
b100 %
#421
b101 %
b0000000000000000 &
#422
b110 %
#423
b111 %
b0000000000000010 &
#424
b000 %
b1000011010100000 &
#425
b001 %
b0111100101100000 &
#426
b010 %
b0000000000000000 &
#427
b011 %
b1000011010100000 &
#428
b100 %
#429
b101 %
b0000000000000000 &
#430
b110 %
#431
b111 %
b0000000000000010 &
#432
b000 %
b1000011010100000 &
#433
b001 %
b0111100101100000 &
#434
b010 %
b0000000000000000 &
#435
b011 %
b1000011010100000 &
#436
b100 %
#437
b101 %
b0000000000000000 &
#438
b110 %
#439
b111 %
b0000000000000010 &
#440
b000 %
b1000011010100000 &
#441
b001 %
b0111100101100000 &
#442
b010 %
b0000000000000000 &
#443
b011 %
b1000011010100000 &
#444
b100 %
#445
b101 %
b0000000000000000 &
#446
b110 %
#447
b111 %
b0000000000000010 &
#448
b000 %
b1000011010100000 &
#449
b001 %
b0111100101100000 &
#450
b010 %
b0000000000000000 &
#451
b011 %
b1000011010100000 &
#452
b100 %
#453
b101 %
b0000000000000000 &
#454
b110 %
#455
b111 %
b0000000000000010 &
#456
b000 %
b1000011010100000 &
#457
b001 %
b0111100101100000 &
#458
b010 %
b0000000000000000 &
#459
b011 %
b1000011010100000 &
#460
b100 %
#461
b101 %
b0000000000000000 &
#462
b110 %
#463
b111 %
b0000000000000010 &
#464
b000 %
b1000011010100000 &
#465
b001 %
b0111100101100000 &
#466
b010 %
b0000000000000000 &
#467
b011 %
b1000011010100000 &
#468
b100 %
#469
b101 %
b0000000000000000 &
#470
b110 %
#471
b111 %
b0000000000000010 &
#472
b000 %
b1000011010100000 &
#473
b001 %
b0111100101100000 &
#474
b010 %
b0000000000000000 &
#475
b011 %
b1000011010100000 &
#476
b100 %
#477
b101 %
b0000000000000000 &
#478
b110 %
#479
b111 %
b0000000000000010 &
#480
b000 %
b1000011010100000 &
#481
b001 %
b0111100101100000 &
#482
b010 %
b0000000000000000 &
#483
b011 %
b1000011010100000 &
#484
b100 %
#485
b101 %
b0000000000000000 &
#486
b110 %
#487
b111 %
b0000000000000010 &
#488
b000 %
b1000011010100000 &
#489
b001 %
b0111100101100000 &
#490
b010 %
b0000000000000000 &
#491
b011 %
b1000011010100000 &
#492
b100 %
#493
b101 %
b0000000000000000 &
#494
b110 %
#495
b111 %
b0000000000000010 &
#496
b000 %
b1000011010100000 &
#497
b001 %
b0111100101100000 &
#498
b010 %
b0000000000000000 &
#499
b011 %
b1000011010100000 &
#500
b100 %
#501
b101 %
b0000000000000000 &
#502
b110 %
#503
b111 %
b0000000000000010 &
#504
b000 %
b1000011010100000 &
#505
b001 %
b0111100101100000 &
#506
b010 %
b0000000000000000 &
#507
b011 %
b1000011010100000 &
#508
b100 %
#509
b101 %
b0000000000000000 &
#510
b110 %
#511
b111 %
b0000000000000010 &
#512
b000 %
b1000011010100000 &
#513
b001 %
b0111100101100000 &
#514
b010 %
b0000000000000000 &
#515
b011 %
b1000011010100000 &
#516
b100 %
#517
b101 %
b0000000000000000 &
#518
b110 %
#519
b111 %
b0000000000000010 &
#520
b000 %
b1000011010100000 &
#521
b001 %
b0111100101100000 &
#522
b010 %
b0000000000000000 &
#523
b011 %
b1000011010100000 &
#524
b100 %
#525
b101 %
b0000000000000000 &
#526
b110 %
#527
b111 %
b0000000000000010 &
#528
b000 %
b1000011010100000 &
#529
b001 %
b0111100101100000 &
#530
b010 %
b0000000000000000 &
#531
b011 %
b1000011010100000 &
#532
b100 %
#533
b101 %
b0000000000000000 &
#534
b110 %
#535
b111 %
b0000000000000010 &
#536
b000 %
b1000011010100000 &
#537
b001 %
b0111100101100000 &
#538
b010 %
b0000000000000000 &
#539
b011 %
b1000011010100000 &
#540
b100 %
#541
b101 %
b0000000000000000 &
#542
b110 %
#543
b111 %
b0000000000000010 &
#544
b000 %
b1000011010100000 &
#545
b001 %
b0111100101100000 &
#546
b010 %
b0000000000000000 &
#547
b011 %
b1000011010100000 &
#548
b100 %
#549
b101 %
b0000000000000000 &
#550
b110 %
#551
b111 %
b0000000000000010 &
#552
b000 %
b1000011010100000 &
#553
b001 %
b0111100101100000 &
#554
b010 %
b0000000000000000 &
#555
b011 %
b1000011010100000 &
#556
b100 %
#557
b101 %
b0000000000000000 &
#558
b110 %
#559
b111 %
b0000000000000010 &
#560
b000 %
b1000011010100000 &
#561
b001 %
b0111100101100000 &
#562
b010 %
b0000000000000000 &
#563
b011 %
b1000011010100000 &
#564
b100 %
#565
b101 %
b0000000000000000 &
#566
b110 %
#567
b111 %
b0000000000000010 &
#568
b000 %
b1000011010100000 &
#569
b001 %
b0111100101100000 &
#570
b010 %
b0000000000000000 &
#571
b011 %
b1000011010100000 &
#572
b100 %
#573
b101 %
b0000000000000000 &
#574
b110 %
#575
b111 %
b0000000000000010 &
#576
b000 %
b1000011010100000 &
#577
b001 %
b0111100101100000 &
#578
b010 %
b0000000000000000 &
#579
b011 %
b1000011010100000 &
#580
b100 %
#581
b101 %
b0000000000000000 &
#582
b110 %
#583
b111 %
b0000000000000010 &
#584
b000 %
b1000011010100000 &
#585
b001 %
b0111100101100000 &
#586
b010 %
b0000000000000000 &
#587
b011 %
b1000011010100000 &
#588
b100 %
#589
b101 %
b0000000000000000 &
#590
b110 %
#591
b111 %
b0000000000000010 &
#592
b000 %
b1000011010100000 &
#593
b001 %
b0111100101100000 &
#594
b010 %
b0000000000000000 &
#595
b011 %
b1000011010100000 &
#596
b100 %
#597
b101 %
b0000000000000000 &
#598
b110 %
#599
b111 %
b0000000000000010 &
#600
b000 %
b1000011010100000 &
#601
b001 %
b0111100101100000 &
#602
b010 %
b0000000000000000 &
#603
b011 %
b1000011010100000 &
#604
b100 %
#605
b101 %
b0000000000000000 &
#606
b110 %
#607
b111 %
b0000000000000010 &
#608
b000 %
b1000011010100000 &
#609
b001 %
b0111100101100000 &
#610
b010 %
b0000000000000000 &
#611
b011 %
b1000011010100000 &
#612
b100 %
#613
b101 %
b0000000000000000 &
#614
b110 %
#615
b111 %
b0000000000000010 &
#616
b000 %
b1000011010100000 &
#617
b001 %
b0111100101100000 &
#618
b010 %
b0000000000000000 &
#619
b011 %
b1000011010100000 &
#620
b100 %
#621
b101 %
b0000000000000000 &
#622
b110 %
#623
b111 %
b0000000000000010 &
#624
b000 %
b1000011010100000 &
#625
b001 %
b0111100101100000 &
#626
b010 %
b0000000000000000 &
#627
b011 %
b1000011010100000 &
#628
b100 %
#629
b101 %
b0000000000000000 &
#630
b110 %
#631
b111 %
b0000000000000010 &
#632
b000 %
b1000011010100000 &
#633
b001 %
b0111100101100000 &
#634
b010 %
b0000000000000000 &
#635
b011 %
b1000011010100000 &
#636
b100 %
#637
b101 %
b0000000000000000 &
#638
b110 %
#639
b111 %
b0000000000000010 &
#640
b000 %
b1000011010100000 &
#641
b001 %
b0111100101100000 &
#642
b010 %
b0000000000000000 &
#643
b011 %
b1000011010100000 &
#644
b100 %
#645
b101 %
b0000000000000000 &
#646
b110 %
#647
b111 %
b0000000000000010 &
#648
b000 %
b1000011010100000 &
#649
b001 %
b0111100101100000 &
#650
b010 %
b0000000000000000 &
#651
b011 %
b1000011010100000 &
#652
b100 %
#653
b101 %
b0000000000000000 &
#654
b110 %
#655
b111 %
b0000000000000010 &
#656
b000 %
b1000011010100000 &
#657
b001 %
b0111100101100000 &
#658
b010 %
b0000000000000000 &
#659
b011 %
b1000011010100000 &
#660
b100 %
#661
b101 %
b0000000000000000 &
#662
b110 %
#663
b111 %
b0000000000000010 &
#664
b000 %
b1000011010100000 &
#665
b001 %
b0111100101100000 &
#666
b010 %
b0000000000000000 &
#667
b011 %
b1000011010100000 &
#668
b100 %
#669
b101 %
b0000000000000000 &
#670
b110 %
#671
b111 %
b0000000000000010 &
#672
b000 %
b1000011010100000 &
#673
b001 %
b0111100101100000 &
#674
b010 %
b0000000000000000 &
#675
b011 %
b1000011010100000 &
#676
b100 %
#677
b101 %
b0000000000000000 &
#678
b110 %
#679
b111 %
b0000000000000010 &
#680
b000 %
b1000011010100000 &
#681
b001 %
b0111100101100000 &
#682
b010 %
b0000000000000000 &
#683
b011 %
b1000011010100000 &
#684
b100 %
#685
b101 %
b0000000000000000 &
#686
b110 %
#687
b111 %
b0000000000000010 &
#688
b000 %
b1000011010100000 &
#689
b001 %
b0111100101100000 &
#690
b010 %
b0000000000000000 &
#691
b011 %
b1000011010100000 &
#692
b100 %
#693
b101 %
b0000000000000000 &
#694
b110 %
#695
b111 %
b0000000000000010 &
#696
b000 %
b1000011010100000 &
#697
b001 %
b0111100101100000 &
#698
b010 %
b0000000000000000 &
#699
b011 %
b1000011010100000 &
#700
b100 %
#701
b101 %
b0000000000000000 &
#702
b110 %
#703
b111 %
b0000000000000010 &
#704
b000 %
b1000011010100000 &
#705
b001 %
b0111100101100000 &
#706
b010 %
b0000000000000000 &
#707
b011 %
b1000011010100000 &
#708
b100 %
#709
b101 %
b0000000000000000 &
#710
b110 %
#711
b111 %
b0000000000000010 &
#712
b000 %
b1000011010100000 &
#713
b001 %
b0111100101100000 &
#714
b010 %
b0000000000000000 &
#715
b011 %
b1000011010100000 &
#716
b100 %
#717
b101 %
b0000000000000000 &
#718
b110 %
#719
b111 %
b0000000000000010 &
#720
b000 %
b1000011010100000 &
#721
b001 %
b0111100101100000 &
#722
b010 %
b0000000000000000 &
#723
b011 %
b1000011010100000 &
#724
b100 %
#725
b101 %
b0000000000000000 &
#726
b110 %
#727
b111 %
b0000000000000010 &
#728
b000 %
b1000011010100000 &
#729
b001 %
b0111100101100000 &
#730
b010 %
b0000000000000000 &
#731
b011 %
b1000011010100000 &
#732
b100 %
#733
b101 %
b0000000000000000 &
#734
b110 %
#735
b111 %
b0000000000000010 &
#736
b000 %
b1000011010100000 &
#737
b001 %
b0111100101100000 &
#738
b010 %
b0000000000000000 &
#739
b011 %
b1000011010100000 &
#740
b100 %
#741
b101 %
b0000000000000000 &
#742
b110 %
#743
b111 %
b0000000000000010 &
#744
b000 %
b1000011010100000 &
#745
b001 %
b0111100101100000 &
#746
b010 %
b0000000000000000 &
#747
b011 %
b1000011010100000 &
#748
b100 %
#749
b101 %
b0000000000000000 &
#750
b110 %
#751
b111 %
b0000000000000010 &
#752
b000 %
b1000011010100000 &
#753
b001 %
b0111100101100000 &
#754
b010 %
b0000000000000000 &
#755
b011 %
b1000011010100000 &
#756
b100 %
#757
b101 %
b0000000000000000 &
#758
b110 %
#759
b111 %
b0000000000000010 &
#760
b000 %
b1000011010100000 &
#761
b001 %
b0111100101100000 &
#762
b010 %
b0000000000000000 &
#763
b011 %
b1000011010100000 &
#764
b100 %
#765
b101 %
b0000000000000000 &
#766
b110 %
#767
b111 %
b0000000000000010 &
#768
b000 %
b1000011010100000 &
#769
b001 %
b0111100101100000 &
#770
b010 %
b0000000000000000 &
#771
b011 %
b1000011010100000 &
#772
b100 %
#773
b101 %
b0000000000000000 &
#774
b110 %
#775
b111 %
b0000000000000010 &
#776
b000 %
b1000011010100000 &
#777
b001 %
b0111100101100000 &
#778
b010 %
b0000000000000000 &
#779
b011 %
b1000011010100000 &
#780
b100 %
#781
b101 %
b0000000000000000 &
#782
b110 %
#783
b111 %
b0000000000000010 &
#784
b000 %
b1000011010100000 &
#785
b001 %
b0111100101100000 &
#786
b010 %
b0000000000000000 &
#787
b011 %
b1000011010100000 &
#788
b100 %
#789
b101 %
b0000000000000000 &
#790
b110 %
#791
b111 %
b0000000000000010 &
#792
b000 %
b1000011010100000 &
#793
b001 %
b0111100101100000 &
#794
b010 %
b0000000000000000 &
#795
b011 %
b1000011010100000 &
#796
b100 %
#797
b101 %
b0000000000000000 &
#798
b110 %
#799
b111 %
b0000000000000010 &
#800
b000 %
b1000011010100000 &
#801
b001 %
b0111100101100000 &
#802
b010 %
b0000000000000000 &
#803
b011 %
b1000011010100000 &
#804
b100 %
#805
b101 %
b0000000000000000 &
#806
b110 %
#807
b111 %
b0000000000000010 &
#808
b000 %
b1000011010100000 &
#809
b001 %
b0111100101100000 &
#810
b010 %
b0000000000000000 &
#811
b011 %
b1000011010100000 &
#812
b100 %
#813
b101 %
b0000000000000000 &
#814
b110 %
#815
b111 %
b0000000000000010 &
#816
b000 %
b1000011010100000 &
#817
b001 %
b0111100101100000 &
#818
b010 %
b0000000000000000 &
#819
b011 %
b1000011010100000 &
#820
b100 %
#821
b101 %
b0000000000000000 &
#822
b110 %
#823
b111 %
b0000000000000010 &
#824
b000 %
b1000011010100000 &
#825
b001 %
b0111100101100000 &
#826
b010 %
b0000000000000000 &
#827
b011 %
b1000011010100000 &
#828
b100 %
#829
b101 %
b0000000000000000 &
#830
b110 %
#831
b111 %
b0000000000000010 &
#832
b000 %
b1000011010100000 &
#833
b001 %
b0111100101100000 &
#834
b010 %
b0000000000000000 &
#835
b011 %
b1000011010100000 &
#836
b100 %
#837
b101 %
b0000000000000000 &
#838
b110 %
#839
b111 %
b0000000000000010 &
#840
b000 %
b1000011010100000 &
#841
b001 %
b0111100101100000 &
#842
b010 %
b0000000000000000 &
#843
b011 %
b1000011010100000 &
#844
b100 %
#845
b101 %
b0000000000000000 &
#846
b110 %
#847
b111 %
b0000000000000010 &
#848
b000 %
b1000011010100000 &
#849
b001 %
b0111100101100000 &
#850
b010 %
b0000000000000000 &
#851
b011 %
b1000011010100000 &
#852
b100 %
#853
b101 %
b0000000000000000 &
#854
b110 %
#855
b111 %
b0000000000000010 &
#856
b000 %
b1000011010100000 &
#857
b001 %
b0111100101100000 &
#858
b010 %
b0000000000000000 &
#859
b011 %
b1000011010100000 &
#860
b100 %
#861
b101 %
b0000000000000000 &
#862
b110 %
#863
b111 %
b0000000000000010 &
#864
b000 %
b1000011010100000 &
#865
b001 %
b0111100101100000 &
#866
b010 %
b0000000000000000 &
#867
b011 %
b1000011010100000 &
#868
b100 %
#869
b101 %
b0000000000000000 &
#870
b110 %
#871
b111 %
b0000000000000010 &
#872
b000 %
b1000011010100000 &
#873
b001 %
b0111100101100000 &
#874
b010 %
b0000000000000000 &
#875
b011 %
b1000011010100000 &
#876
b100 %
#877
b101 %
b0000000000000000 &
#878
b110 %
#879
b111 %
b0000000000000010 &
#880
b000 %
b1000011010100000 &
#881
b001 %
b0111100101100000 &
#882
b010 %
b0000000000000000 &
#883
b011 %
b1000011010100000 &
#884
b100 %
#885
b101 %
b0000000000000000 &
#886
b110 %
#887
b111 %
b0000000000000010 &
#888
b000 %
b1000011010100000 &
#889
b001 %
b0111100101100000 &
#890
b010 %
b0000000000000000 &
#891
b011 %
b1000011010100000 &
#892
b100 %
#893
b101 %
b0000000000000000 &
#894
b110 %
#895
b111 %
b0000000000000010 &
#896
b000 %
b1000011010100000 &
#897
b001 %
b0111100101100000 &
#898
b010 %
b0000000000000000 &
#899
b011 %
b1000011010100000 &
#900
b100 %
#901
b101 %
b0000000000000000 &
#902
b110 %
#903
b111 %
b0000000000000010 &
#904
b000 %
b1000011010100000 &
#905
b001 %
b0111100101100000 &
#906
b010 %
b0000000000000000 &
#907
b011 %
b1000011010100000 &
#908
b100 %
