level_4/better_processor/rtl/FetchUnit.sv
module FetchUnit(
    input clk,
    input reset,
    input en_pc,
    input [11:0] new_pc,
    input en_new_pc,
    output reg [15:0] instruction
);
    reg [11:0] pc;
    reg [15:0] memory [4095:0];

    initial begin
        $readmemh("./Instruction_Generator/instructions.txt", memory);
    end

    always @(posedge clk or posedge reset) begin
        if (reset) begin
            pc <= 0;
        end else if(en_new_pc) begin
            pc <= new_pc;
            instruction <= memory[pc];
        end else if (en_pc) begin
            pc <= pc + 1;
            instruction <= memory[pc];
        end
    end

endmodule

level_4/better_processor/trace_fetch.vcd
$version Generated by VerilatedVcd $end
$timescale 1ps $end
 $scope module TOP $end
  $var wire 1 # clk $end
  $var wire 1 $ reset $end
  $var wire 1 % en_pc $end
  $var wire 12 & new_pc [11:0] $end
  $var wire 1 ' en_new_pc $end
  $var wire 16 ( instruction [15:0] $end
  $scope module FetchUnit $end
   $var wire 1 # clk $end
   $var wire 1 $ reset $end
   $var wire 1 % en_pc $end
   $var wire 12 & new_pc [11:0] $end
   $var wire 1 ' en_new_pc $end
   $var wire 16 ( instruction [15:0] $end
   $var wire 12 ) pc [11:0] $end
  $upscope $end
 $upscope $end
$enddefinitions $end


#0
1#
0$
1%
b000000000000 &
0'
b0000000000000000 (
b000000000000 )
#1
0#
#2
1#
b0100000110100111 (
b000000000001 )
#3
0#
#4
1#
b0011101011110001 (
b000000000010 )
#5
0#
#6
1#
b1010110011011001 (
b000000000011 )
#7
0#
#8
1#
b0010101100010001 (
b000000000100 )
#9
0#
#10
1#
b000000000101 )
#11
0#
#12
1#
b1101101011001000 (
b000000000110 )
#13
0#
#14
1#
b1000111011011000 (
b000000000111 )
#15
0#
#16
1#
b0000100111111110 (
b000000001000 )
#17
0#
#18
1#
b0010111101000011 (
b000000001001 )
#19
0#
#20
1#
b0000010001001101 (
b000000001010 )
#21
0#
#22
1#
b1001100010011000 (
b000000001011 )
#23
0#
#24
1#
b0011110001010101 (
b000000001100 )
#25
0#
#26
1#
b0001001010001100 (
b000000001101 )
#27
0#
#28
1#
b1101101111100010 (
b000000001110 )
#29
0#
#30
1#
b1101010010110011 (
b000000001111 )
#31
0#
#32
1#
b0011011101000111 (
b000000010000 )
#33
0#
#34
1#
b0011100100010111 (
b000000010001 )
#35
0#
#36
1#
b0100000100010001 (
b000000010010 )
#37
0#
#38
1#
b1100001110011000 (
b000000010011 )
#39
0#
#40
1#
b0100100101010100 (
b000000010100 )
#41
0#
#42
1#
b0010111000101111 (
b000000010101 )
#43
0#
#44
1#
b0010101100010001 (
b000000010110 )
#45
0#
#46
1#
b1001011000101101 (
b000000010111 )
#47
0#
#48
1#
b1000101100000101 (
b000000011000 )
#49
0#
#50
1#
b0011001001011000 (
b000000011001 )
#51
0#
#52
1#
b0110011011110101 (
b000000011010 )
#53
0#
#54
1#
b1000000101101011 (
b000000011011 )
#55
0#
#56
1#
b1001110111010110 (
b000000011100 )
#57
0#
#58
1#
b0111011110001000 (
b000000011101 )
#59
0#
#60
1#
b1001110100000111 (
b000000011110 )
#61
0#
#62
1#
b0110010010011001 (
b000000011111 )
#63
0#
#64
1#
b1011010010010010 (
b000000100000 )
#65
0#
#66
1#
b0000111101001000 (
b000000100001 )
#67
0#
#68
1#
b0101000100110011 (
b000000100010 )
#69
0#
#70
1#
b1110111001100010 (
b000000100011 )
#71
0#
#72
1#
b1001010001000001 (
b000000100100 )
#73
0#
#74
1#
b0100110011110011 (
b000000100101 )
#75
0#
#76
1#
b0000111100001101 (
b000000100110 )
#77
0#
#78
1#
b0101000000100011 (
b000000100111 )
#79
0#
#80
1#
b0110101011100101 (
b000000101000 )
#81
0#
#82
1#
b1111100001011111 (
b000000101001 )
#83
0#
#84
1#
b0011010100110000 (
b000000101010 )
#85
0#
#86
1#
b0010001011010001 (
b000000101011 )
#87
0#
#88
1#
b1111011011001000 (
b000000101100 )
#89
0#
#90
1#
b1111010111101101 (
b000000101101 )
#91
0#
#92
1#
b1100010101100001 (
b000000101110 )
#93
0#
#94
1#
b0110100000001100 (
b000000101111 )
#95
0#
#96
1#
b0001010101001011 (
b000000110000 )
#97
0#
#98
1#
b0010100100000010 (
b000000110001 )
