level_4/better_processor/rtl/FetchUnit.sv
module FetchUnit(
    input clk,
    input reset,
    input en_pc,
    output reg [15:0] instruction
);
    reg [7:0] pc;
    reg [15:0] memory [255:0];

    initial begin
        $readmemh("./Instruction_Generator/instructions.txt", memory);
    end

    always @(posedge clk or posedge reset) begin
        if (reset) begin
            pc <= 0;
        end else if (en_pc) begin
            pc <= pc + 1;
        end
    end

    always @(posedge clk) begin
        if (en_pc) begin
            instruction <= memory[pc];
            //$display("program counter is %d", pc);
        end
    end
endmodule

level_4/better_processor/trace_fetch.vcd
$version Generated by VerilatedVcd $end
$timescale 1ps $end
 $scope module TOP $end
  $var wire 1 # clk $end
  $var wire 1 $ reset $end
  $var wire 1 % en_pc $end
  $var wire 16 & instruction [15:0] $end
  $scope module FetchUnit $end
   $var wire 1 # clk $end
   $var wire 1 $ reset $end
   $var wire 1 % en_pc $end
   $var wire 16 & instruction [15:0] $end
   $var wire 8 ' pc [7:0] $end
  $upscope $end
 $upscope $end
$enddefinitions $end


#0
1#
0$
1%
b0000000000000000 &
b00000000 '
#1
0#
#2
1#
b0100000110100111 &
b00000001 '
#3
0#
#4
1#
b0100101111000111 &
b00000010 '
#5
0#
#6
1#
b0000110110010001 &
b00000011 '
#7
0#
#8
1#
b0100011011011111 &
b00000100 '
#9
0#
#10
1#
b1111101110110011 &
b00000101 '
#11
0#
#12
1#
b1111011011001110 &
b00000110 '
#13
0#
#14
1#
b1001010011011101 &
b00000111 '
#15
0#
#16
1#
b0110000011100011 &
b00001000 '
#17
0#
#18
1#
b1000011000110110 &
b00001001 '
#19
0#
#20
1#
b0111101111110001 &
b00001010 '
#21
0#
#22
1#
b1100100110101110 &
b00001011 '
#23
0#
#24
1#
b0111111011010001 &
b00001100 '
#25
0#
#26
1#
b0111110011101001 &
b00001101 '
#27
0#
#28
1#
b1110000001001110 &
b00001110 '
#29
0#
#30
1#
b1101101110001010 &
b00001111 '
#31
0#
#32
1#
b0111101100010100 &
b00010000 '
#33
0#
#34
1#
b1000111011111111 &
b00010001 '
#35
0#
#36
1#
b0100001000001101 &
b00010010 '
#37
0#
#38
1#
b1111010010101011 &
b00010011 '
#39
0#
#40
1#
b0101000111100010 &
b00010100 '
#41
0#
#42
1#
b0110001110011111 &
b00010101 '
#43
0#
#44
1#
b1000001011111001 &
b00010110 '
#45
0#
#46
1#
b1110000110010000 &
b00010111 '
#47
0#
#48
1#
b0000001000011110 &
b00011000 '
#49
0#
#50
1#
b1001111010100111 &
b00011001 '
#51
0#
#52
1#
b1010101001100111 &
b00011010 '
#53
0#
#54
1#
b1000110100110000 &
b00011011 '
#55
0#
#56
1#
b1111000110001001 &
b00011100 '
#57
0#
#58
1#
b1010110011000111 &
b00011101 '
#59
0#
#60
1#
b1111011011000111 &
b00011110 '
#61
0#
#62
1#
b1101100100011110 &
b00011111 '
#63
0#
#64
1#
b0001011000100010 &
b00100000 '
#65
0#
#66
1#
b0011000011100000 &
b00100001 '
#67
0#
#68
1#
b0101011101000110 &
b00100010 '
#69
0#
#70
1#
b0100110010011010 &
b00100011 '
#71
0#
#72
1#
b1011111001000100 &
b00100100 '
#73
0#
#74
1#
b1001110111101101 &
b00100101 '
#75
0#
#76
1#
b0110111111011111 &
b00100110 '
#77
0#
#78
1#
b1100111011111101 &
b00100111 '
#79
0#
#80
1#
b1001100110101000 &
b00101000 '
#81
0#
#82
1#
b0001011111111110 &
b00101001 '
#83
0#
#84
1#
b1011001011110100 &
b00101010 '
#85
0#
#86
1#
b0111111101010001 &
b00101011 '
#87
0#
#88
1#
b0101011100110110 &
b00101100 '
#89
0#
#90
1#
b0100100101010010 &
b00101101 '
#91
0#
#92
1#
b1100111010101110 &
b00101110 '
#93
0#
#94
1#
b1011100011100101 &
b00101111 '
#95
0#
#96
1#
b1000011010001001 &
b00110000 '
#97
0#
#98
1#
b0100101111101010 &
b00110001 '
