level_4/lab_1/ALU.sv
module ALU (
    input wire carry_in,
    input wire [15:0] in_a,
    input wire [15:0] in_b,
    input wire [3:0] select,
    input wire mode,
    output reg carry_out,
    output reg compare,
    output reg [15:0] alu_out
);
    reg [15:0] alu_result;
    
    always @(*) begin
        if (mode) begin
            case (select)
                4'd0: alu_result = ~in_a;
                4'd1: alu_result = ~(in_a | in_b);
                4'd2: alu_result = (~in_a) & in_b;
                4'd3: alu_result = 0;
                4'd4: alu_result = ~(in_a & in_b);
                4'd5: alu_result = ~in_b;
                4'd6: alu_result = in_a ^ in_b;
                4'd7: alu_result = in_a & (~in_b);
                4'd8: alu_result = ~in_a | in_b;
                4'd9: alu_result = ~(in_a ^ in_b);
                4'd10: alu_result = in_b;
                4'd11: alu_result = in_a & in_b;
                4'd12: alu_result = 1;
                4'd13: alu_result = in_a | ~in_b;
                4'd14: alu_result = in_a | in_b;
                4'd15: alu_result = in_a;
            endcase
        end else begin
            case (select)
                4'd0: alu_result = in_a;
                4'd1: alu_result = in_a | in_b;
                4'd2: alu_result = in_a | ~in_b;
                4'd3: alu_result = -1;
                4'd4: alu_result = in_a | (in_a & ~in_b);
                4'd5: alu_result = (in_a | in_b) + (in_a & ~in_b);
                4'd6: alu_result = in_a - in_b - 1;
                4'd7: alu_result = (in_a & ~in_b) - 1;
                4'd8: alu_result = in_a + (in_a & in_b);
                4'd9: alu_result = in_a + in_b;
                4'd10: alu_result = (in_a | (~in_b)) + (in_a & in_b);
                4'd11: alu_result = (in_a & in_b) - 1;
                4'd12: alu_result = in_a + in_a;
                4'd13: alu_result = (in_a | in_b) + in_a;
                4'd14: alu_result = (in_a | (~in_b)) + in_a;
                4'd15: alu_result = in_a - 1;
            endcase
        end
        alu_out = alu_result;
        carry_out = carry_in;
        compare = (in_a == in_b) ? 1 : 0;
    end
endmodule

level_4/lab_1/trace.vcd
$version Generated by VerilatedVcd $end
$timescale 1ps $end
 $scope module TOP $end
  $var wire 1 # carry_in $end
  $var wire 16 $ in_a [15:0] $end
  $var wire 16 % in_b [15:0] $end
  $var wire 4 & select [3:0] $end
  $var wire 1 ' mode $end
  $var wire 1 ( carry_out $end
  $var wire 1 ) compare $end
  $var wire 16 * alu_out [15:0] $end
  $scope module ALU $end
   $var wire 1 # carry_in $end
   $var wire 16 $ in_a [15:0] $end
   $var wire 16 % in_b [15:0] $end
   $var wire 4 & select [3:0] $end
   $var wire 1 ' mode $end
   $var wire 1 ( carry_out $end
   $var wire 1 ) compare $end
   $var wire 16 * alu_out [15:0] $end
   $var wire 16 + alu_result [15:0] $end
  $upscope $end
 $upscope $end
$enddefinitions $end


#0
0#
b0000000000001010 $
b0000000000000011 %
b0000 &
0'
0(
0)
b0000000000001010 *
b0000000000001010 +
#1
b0001 &
b0000000000001011 *
b0000000000001011 +
#2
b0010 &
b1111111111111110 *
b1111111111111110 +
#3
b0011 &
b1111111111111111 *
b1111111111111111 +
#4
b0100 &
b0000000000001010 *
b0000000000001010 +
#5
b0101 &
b0000000000010011 *
b0000000000010011 +
#6
b0110 &
b0000000000000110 *
b0000000000000110 +
#7
b0111 &
b0000000000000111 *
b0000000000000111 +
#8
b1000 &
b0000000000001100 *
b0000000000001100 +
#9
b1001 &
b0000000000001101 *
b0000000000001101 +
#10
b1010 &
b0000000000000000 *
b0000000000000000 +
#11
b1011 &
b0000000000000001 *
b0000000000000001 +
#12
b1100 &
b0000000000010100 *
b0000000000010100 +
#13
b1101 &
b0000000000010101 *
b0000000000010101 +
#14
b1110 &
b0000000000001000 *
b0000000000001000 +
#15
b1111 &
b0000000000001001 *
b0000000000001001 +
#16
b0000 &
b0000000000001010 *
b0000000000001010 +
#17
b0001 &
b0000000000001011 *
b0000000000001011 +
#18
b0010 &
b1111111111111110 *
b1111111111111110 +
#19
b0011 &
b1111111111111111 *
b1111111111111111 +
#20
b0100 &
b0000000000001010 *
b0000000000001010 +
#21
b0101 &
b0000000000010011 *
b0000000000010011 +
#22
b0110 &
b0000000000000110 *
b0000000000000110 +
#23
b0111 &
b0000000000000111 *
b0000000000000111 +
#24
b1000 &
b0000000000001100 *
b0000000000001100 +
#25
b1001 &
b0000000000001101 *
b0000000000001101 +
#26
b1010 &
b0000000000000000 *
b0000000000000000 +
#27
b1011 &
b0000000000000001 *
b0000000000000001 +
#28
b1100 &
b0000000000010100 *
b0000000000010100 +
#29
b1101 &
b0000000000010101 *
b0000000000010101 +
#30
b1110 &
b0000000000001000 *
b0000000000001000 +
#31
b1111 &
b0000000000001001 *
b0000000000001001 +
#32
b0000 &
b0000000000001010 *
b0000000000001010 +
#33
b0001 &
b0000000000001011 *
b0000000000001011 +
#34
b0010 &
b1111111111111110 *
b1111111111111110 +
#35
b0011 &
b1111111111111111 *
b1111111111111111 +
#36
b0100 &
b0000000000001010 *
b0000000000001010 +
#37
b0101 &
b0000000000010011 *
b0000000000010011 +
#38
b0110 &
b0000000000000110 *
b0000000000000110 +
#39
b0111 &
b0000000000000111 *
b0000000000000111 +
#40
b1000 &
b0000000000001100 *
b0000000000001100 +
#41
b1001 &
b0000000000001101 *
b0000000000001101 +
#42
b1010 &
b0000000000000000 *
b0000000000000000 +
#43
b1011 &
b0000000000000001 *
b0000000000000001 +
#44
b1100 &
b0000000000010100 *
b0000000000010100 +
#45
b1101 &
b0000000000010101 *
b0000000000010101 +
#46
b1110 &
b0000000000001000 *
b0000000000001000 +
#47
b1111 &
b0000000000001001 *
b0000000000001001 +
#48
b0000 &
b0000000000001010 *
b0000000000001010 +
#49
b0001 &
b0000000000001011 *
b0000000000001011 +
#50
b0010 &
b1111111111111110 *
b1111111111111110 +
#51
b0011 &
b1111111111111111 *
b1111111111111111 +
#52
b0100 &
b0000000000001010 *
b0000000000001010 +
#53
b0101 &
b0000000000010011 *
b0000000000010011 +
#54
b0110 &
b0000000000000110 *
b0000000000000110 +
#55
b0111 &
b0000000000000111 *
b0000000000000111 +
#56
b1000 &
b0000000000001100 *
b0000000000001100 +
#57
b1001 &
b0000000000001101 *
b0000000000001101 +
#58
b1010 &
b0000000000000000 *
b0000000000000000 +
#59
b1011 &
b0000000000000001 *
b0000000000000001 +
#60
b1100 &
b0000000000010100 *
b0000000000010100 +
#61
b1101 &
b0000000000010101 *
b0000000000010101 +
#62
b1110 &
b0000000000001000 *
b0000000000001000 +
#63
b1111 &
b0000000000001001 *
b0000000000001001 +
#64
b0000 &
b0000000000001010 *
b0000000000001010 +
#65
b0001 &
b0000000000001011 *
b0000000000001011 +
#66
b0010 &
b1111111111111110 *
b1111111111111110 +
#67
b0011 &
b1111111111111111 *
b1111111111111111 +
#68
b0100 &
b0000000000001010 *
b0000000000001010 +
#69
b0101 &
b0000000000010011 *
b0000000000010011 +
#70
b0110 &
b0000000000000110 *
b0000000000000110 +
#71
b0111 &
b0000000000000111 *
b0000000000000111 +
#72
b1000 &
b0000000000001100 *
b0000000000001100 +
#73
b1001 &
b0000000000001101 *
b0000000000001101 +
#74
b1010 &
b0000000000000000 *
b0000000000000000 +
#75
b1011 &
b0000000000000001 *
b0000000000000001 +
#76
b1100 &
b0000000000010100 *
b0000000000010100 +
#77
b1101 &
b0000000000010101 *
b0000000000010101 +
#78
b1110 &
b0000000000001000 *
b0000000000001000 +
#79
b1111 &
b0000000000001001 *
b0000000000001001 +
#80
b0000 &
b0000000000001010 *
b0000000000001010 +
#81
b0001 &
b0000000000001011 *
b0000000000001011 +
#82
b0010 &
b1111111111111110 *
b1111111111111110 +
#83
b0011 &
b1111111111111111 *
b1111111111111111 +
#84
b0100 &
b0000000000001010 *
b0000000000001010 +
#85
b0101 &
b0000000000010011 *
b0000000000010011 +
#86
b0110 &
b0000000000000110 *
b0000000000000110 +
#87
b0111 &
b0000000000000111 *
b0000000000000111 +
#88
b1000 &
b0000000000001100 *
b0000000000001100 +
#89
b1001 &
b0000000000001101 *
b0000000000001101 +
#90
b1010 &
b0000000000000000 *
b0000000000000000 +
#91
b1011 &
b0000000000000001 *
b0000000000000001 +
#92
b1100 &
b0000000000010100 *
b0000000000010100 +
#93
b1101 &
b0000000000010101 *
b0000000000010101 +
#94
b1110 &
b0000000000001000 *
b0000000000001000 +
#95
b1111 &
b0000000000001001 *
b0000000000001001 +
#96
b0000 &
b0000000000001010 *
b0000000000001010 +
#97
b0001 &
b0000000000001011 *
b0000000000001011 +
#98
b0010 &
b1111111111111110 *
b1111111111111110 +
#99
b0011 &
b1111111111111111 *
b1111111111111111 +
#100
b0100 &
b0000000000001010 *
b0000000000001010 +
#101
b0101 &
b0000000000010011 *
b0000000000010011 +
#102
b0110 &
b0000000000000110 *
b0000000000000110 +
#103
b0111 &
b0000000000000111 *
b0000000000000111 +
#104
b1000 &
b0000000000001100 *
b0000000000001100 +
#105
b1001 &
b0000000000001101 *
b0000000000001101 +
#106
b1010 &
b0000000000000000 *
b0000000000000000 +
#107
b1011 &
b0000000000000001 *
b0000000000000001 +
#108
b1100 &
b0000000000010100 *
b0000000000010100 +
#109
b1101 &
b0000000000010101 *
b0000000000010101 +
#110
b1110 &
b0000000000001000 *
b0000000000001000 +
#111
b1111 &
b0000000000001001 *
b0000000000001001 +
#112
b0000 &
b0000000000001010 *
b0000000000001010 +
#113
b0001 &
b0000000000001011 *
b0000000000001011 +
#114
b0010 &
b1111111111111110 *
b1111111111111110 +
#115
b0011 &
b1111111111111111 *
b1111111111111111 +
#116
b0100 &
b0000000000001010 *
b0000000000001010 +
#117
b0101 &
b0000000000010011 *
b0000000000010011 +
#118
b0110 &
b0000000000000110 *
b0000000000000110 +
#119
b0111 &
b0000000000000111 *
b0000000000000111 +
#120
b1000 &
b0000000000001100 *
b0000000000001100 +
#121
b1001 &
b0000000000001101 *
b0000000000001101 +
#122
b1010 &
b0000000000000000 *
b0000000000000000 +
#123
b1011 &
b0000000000000001 *
b0000000000000001 +
#124
b1100 &
b0000000000010100 *
b0000000000010100 +
#125
b1101 &
b0000000000010101 *
b0000000000010101 +
#126
b1110 &
b0000000000001000 *
b0000000000001000 +
#127
b1111 &
b0000000000001001 *
b0000000000001001 +
#128
b0000 &
b0000000000001010 *
b0000000000001010 +
#129
b0001 &
b0000000000001011 *
b0000000000001011 +
#130
b0010 &
b1111111111111110 *
b1111111111111110 +
#131
b0011 &
b1111111111111111 *
b1111111111111111 +
#132
b0100 &
b0000000000001010 *
b0000000000001010 +
#133
b0101 &
b0000000000010011 *
b0000000000010011 +
#134
b0110 &
b0000000000000110 *
b0000000000000110 +
#135
b0111 &
b0000000000000111 *
b0000000000000111 +
#136
b1000 &
b0000000000001100 *
b0000000000001100 +
#137
b1001 &
b0000000000001101 *
b0000000000001101 +
#138
b1010 &
b0000000000000000 *
b0000000000000000 +
#139
b1011 &
b0000000000000001 *
b0000000000000001 +
#140
b1100 &
b0000000000010100 *
b0000000000010100 +
#141
b1101 &
b0000000000010101 *
b0000000000010101 +
#142
b1110 &
b0000000000001000 *
b0000000000001000 +
#143
b1111 &
b0000000000001001 *
b0000000000001001 +
#144
b0000 &
b0000000000001010 *
b0000000000001010 +
#145
b0001 &
b0000000000001011 *
b0000000000001011 +
#146
b0010 &
b1111111111111110 *
b1111111111111110 +
#147
b0011 &
b1111111111111111 *
b1111111111111111 +
#148
b0100 &
b0000000000001010 *
b0000000000001010 +
#149
b0101 &
b0000000000010011 *
b0000000000010011 +
#150
b0110 &
b0000000000000110 *
b0000000000000110 +
#151
b0111 &
b0000000000000111 *
b0000000000000111 +
#152
b1000 &
b0000000000001100 *
b0000000000001100 +
#153
b1001 &
b0000000000001101 *
b0000000000001101 +
#154
b1010 &
b0000000000000000 *
b0000000000000000 +
#155
b1011 &
b0000000000000001 *
b0000000000000001 +
#156
b1100 &
b0000000000010100 *
b0000000000010100 +
#157
b1101 &
b0000000000010101 *
b0000000000010101 +
#158
b1110 &
b0000000000001000 *
b0000000000001000 +
#159
b1111 &
b0000000000001001 *
b0000000000001001 +
#160
b0000 &
b0000000000001010 *
b0000000000001010 +
#161
b0001 &
b0000000000001011 *
b0000000000001011 +
#162
b0010 &
b1111111111111110 *
b1111111111111110 +
#163
b0011 &
b1111111111111111 *
b1111111111111111 +
#164
b0100 &
b0000000000001010 *
b0000000000001010 +
#165
b0101 &
b0000000000010011 *
b0000000000010011 +
#166
b0110 &
b0000000000000110 *
b0000000000000110 +
#167
b0111 &
b0000000000000111 *
b0000000000000111 +
#168
b1000 &
b0000000000001100 *
b0000000000001100 +
#169
b1001 &
b0000000000001101 *
b0000000000001101 +
#170
b1010 &
b0000000000000000 *
b0000000000000000 +
#171
b1011 &
b0000000000000001 *
b0000000000000001 +
#172
b1100 &
b0000000000010100 *
b0000000000010100 +
#173
b1101 &
b0000000000010101 *
b0000000000010101 +
#174
b1110 &
b0000000000001000 *
b0000000000001000 +
#175
b1111 &
b0000000000001001 *
b0000000000001001 +
#176
b0000 &
b0000000000001010 *
b0000000000001010 +
#177
b0001 &
b0000000000001011 *
b0000000000001011 +
#178
b0010 &
b1111111111111110 *
b1111111111111110 +
#179
b0011 &
b1111111111111111 *
b1111111111111111 +
#180
b0100 &
b0000000000001010 *
b0000000000001010 +
#181
b0101 &
b0000000000010011 *
b0000000000010011 +
#182
b0110 &
b0000000000000110 *
b0000000000000110 +
#183
b0111 &
b0000000000000111 *
b0000000000000111 +
#184
b1000 &
b0000000000001100 *
b0000000000001100 +
#185
b1001 &
b0000000000001101 *
b0000000000001101 +
#186
b1010 &
b0000000000000000 *
b0000000000000000 +
#187
b1011 &
b0000000000000001 *
b0000000000000001 +
#188
b1100 &
b0000000000010100 *
b0000000000010100 +
#189
b1101 &
b0000000000010101 *
b0000000000010101 +
#190
b1110 &
b0000000000001000 *
b0000000000001000 +
#191
b1111 &
b0000000000001001 *
b0000000000001001 +
#192
b0000 &
b0000000000001010 *
b0000000000001010 +
#193
b0001 &
b0000000000001011 *
b0000000000001011 +
#194
b0010 &
b1111111111111110 *
b1111111111111110 +
#195
b0011 &
b1111111111111111 *
b1111111111111111 +
#196
b0100 &
b0000000000001010 *
b0000000000001010 +
#197
b0101 &
b0000000000010011 *
b0000000000010011 +
#198
b0110 &
b0000000000000110 *
b0000000000000110 +
#199
b0111 &
b0000000000000111 *
b0000000000000111 +
#200
b1000 &
b0000000000001100 *
b0000000000001100 +
#201
b1001 &
b0000000000001101 *
b0000000000001101 +
#202
b1010 &
b0000000000000000 *
b0000000000000000 +
#203
b1011 &
b0000000000000001 *
b0000000000000001 +
#204
b1100 &
b0000000000010100 *
b0000000000010100 +
#205
b1101 &
b0000000000010101 *
b0000000000010101 +
#206
b1110 &
b0000000000001000 *
b0000000000001000 +
#207
b1111 &
b0000000000001001 *
b0000000000001001 +
#208
b0000 &
b0000000000001010 *
b0000000000001010 +
#209
b0001 &
b0000000000001011 *
b0000000000001011 +
#210
b0010 &
b1111111111111110 *
b1111111111111110 +
#211
b0011 &
b1111111111111111 *
b1111111111111111 +
#212
b0100 &
b0000000000001010 *
b0000000000001010 +
#213
b0101 &
b0000000000010011 *
b0000000000010011 +
#214
b0110 &
b0000000000000110 *
b0000000000000110 +
#215
b0111 &
b0000000000000111 *
b0000000000000111 +
#216
b1000 &
b0000000000001100 *
b0000000000001100 +
#217
b1001 &
b0000000000001101 *
b0000000000001101 +
#218
b1010 &
b0000000000000000 *
b0000000000000000 +
#219
b1011 &
b0000000000000001 *
b0000000000000001 +
#220
b1100 &
b0000000000010100 *
b0000000000010100 +
#221
b1101 &
b0000000000010101 *
b0000000000010101 +
#222
b1110 &
b0000000000001000 *
b0000000000001000 +
#223
b1111 &
b0000000000001001 *
b0000000000001001 +
#224
b0000 &
b0000000000001010 *
b0000000000001010 +
#225
b0001 &
b0000000000001011 *
b0000000000001011 +
#226
b0010 &
b1111111111111110 *
b1111111111111110 +
#227
b0011 &
b1111111111111111 *
b1111111111111111 +
#228
b0100 &
b0000000000001010 *
b0000000000001010 +
#229
b0101 &
b0000000000010011 *
b0000000000010011 +
#230
b0110 &
b0000000000000110 *
b0000000000000110 +
#231
b0111 &
b0000000000000111 *
b0000000000000111 +
#232
b1000 &
b0000000000001100 *
b0000000000001100 +
#233
b1001 &
b0000000000001101 *
b0000000000001101 +
#234
b1010 &
b0000000000000000 *
b0000000000000000 +
#235
b1011 &
b0000000000000001 *
b0000000000000001 +
#236
b1100 &
b0000000000010100 *
b0000000000010100 +
#237
b1101 &
b0000000000010101 *
b0000000000010101 +
#238
b1110 &
b0000000000001000 *
b0000000000001000 +
#239
b1111 &
b0000000000001001 *
b0000000000001001 +
#240
b0000 &
b0000000000001010 *
b0000000000001010 +
#241
b0001 &
b0000000000001011 *
b0000000000001011 +
#242
b0010 &
b1111111111111110 *
b1111111111111110 +
#243
b0011 &
b1111111111111111 *
b1111111111111111 +
#244
b0100 &
b0000000000001010 *
b0000000000001010 +
#245
b0101 &
b0000000000010011 *
b0000000000010011 +
#246
b0110 &
b0000000000000110 *
b0000000000000110 +
#247
b0111 &
b0000000000000111 *
b0000000000000111 +
#248
b1000 &
b0000000000001100 *
b0000000000001100 +
#249
b1001 &
b0000000000001101 *
b0000000000001101 +
#250
b1010 &
b0000000000000000 *
b0000000000000000 +
#251
b1011 &
b0000000000000001 *
b0000000000000001 +
#252
b1100 &
b0000000000010100 *
b0000000000010100 +
#253
b1101 &
b0000000000010101 *
b0000000000010101 +
#254
b1110 &
b0000000000001000 *
b0000000000001000 +
#255
b1111 &
b0000000000001001 *
b0000000000001001 +
#256
b0000 &
b0000000000001010 *
b0000000000001010 +
#257
b0001 &
b0000000000001011 *
b0000000000001011 +
#258
b0010 &
b1111111111111110 *
b1111111111111110 +
#259
b0011 &
b1111111111111111 *
b1111111111111111 +
#260
b0100 &
b0000000000001010 *
b0000000000001010 +
#261
b0101 &
b0000000000010011 *
b0000000000010011 +
#262
b0110 &
b0000000000000110 *
b0000000000000110 +
#263
b0111 &
b0000000000000111 *
b0000000000000111 +
#264
b1000 &
b0000000000001100 *
b0000000000001100 +
#265
b1001 &
b0000000000001101 *
b0000000000001101 +
#266
b1010 &
b0000000000000000 *
b0000000000000000 +
#267
b1011 &
b0000000000000001 *
b0000000000000001 +
#268
b1100 &
b0000000000010100 *
b0000000000010100 +
#269
b1101 &
b0000000000010101 *
b0000000000010101 +
#270
b1110 &
b0000000000001000 *
b0000000000001000 +
#271
b1111 &
b0000000000001001 *
b0000000000001001 +
#272
b0000 &
b0000000000001010 *
b0000000000001010 +
#273
b0001 &
b0000000000001011 *
b0000000000001011 +
#274
b0010 &
b1111111111111110 *
b1111111111111110 +
#275
b0011 &
b1111111111111111 *
b1111111111111111 +
#276
b0100 &
b0000000000001010 *
b0000000000001010 +
#277
b0101 &
b0000000000010011 *
b0000000000010011 +
#278
b0110 &
b0000000000000110 *
b0000000000000110 +
#279
b0111 &
b0000000000000111 *
b0000000000000111 +
#280
b1000 &
b0000000000001100 *
b0000000000001100 +
#281
b1001 &
b0000000000001101 *
b0000000000001101 +
#282
b1010 &
b0000000000000000 *
b0000000000000000 +
#283
b1011 &
b0000000000000001 *
b0000000000000001 +
#284
b1100 &
b0000000000010100 *
b0000000000010100 +
#285
b1101 &
b0000000000010101 *
b0000000000010101 +
#286
b1110 &
b0000000000001000 *
b0000000000001000 +
#287
b1111 &
b0000000000001001 *
b0000000000001001 +
#288
b0000 &
b0000000000001010 *
b0000000000001010 +
#289
b0001 &
b0000000000001011 *
b0000000000001011 +
#290
b0010 &
b1111111111111110 *
b1111111111111110 +
#291
b0011 &
b1111111111111111 *
b1111111111111111 +
#292
b0100 &
b0000000000001010 *
b0000000000001010 +
#293
b0101 &
b0000000000010011 *
b0000000000010011 +
#294
b0110 &
b0000000000000110 *
b0000000000000110 +
#295
b0111 &
b0000000000000111 *
b0000000000000111 +
#296
b1000 &
b0000000000001100 *
b0000000000001100 +
#297
b1001 &
b0000000000001101 *
b0000000000001101 +
#298
b1010 &
b0000000000000000 *
b0000000000000000 +
#299
b1011 &
b0000000000000001 *
b0000000000000001 +
#300
b1100 &
b0000000000010100 *
b0000000000010100 +
#301
b1101 &
b0000000000010101 *
b0000000000010101 +
#302
b1110 &
b0000000000001000 *
b0000000000001000 +
#303
b1111 &
b0000000000001001 *
b0000000000001001 +
#304
b0000 &
b0000000000001010 *
b0000000000001010 +
#305
b0001 &
b0000000000001011 *
b0000000000001011 +
#306
b0010 &
b1111111111111110 *
b1111111111111110 +
#307
b0011 &
b1111111111111111 *
b1111111111111111 +
#308
b0100 &
b0000000000001010 *
b0000000000001010 +
#309
b0101 &
b0000000000010011 *
b0000000000010011 +
#310
b0110 &
b0000000000000110 *
b0000000000000110 +
#311
b0111 &
b0000000000000111 *
b0000000000000111 +
#312
b1000 &
b0000000000001100 *
b0000000000001100 +
#313
b1001 &
b0000000000001101 *
b0000000000001101 +
#314
b1010 &
b0000000000000000 *
b0000000000000000 +
#315
b1011 &
b0000000000000001 *
b0000000000000001 +
#316
b1100 &
b0000000000010100 *
b0000000000010100 +
#317
b1101 &
b0000000000010101 *
b0000000000010101 +
#318
b1110 &
b0000000000001000 *
b0000000000001000 +
#319
b1111 &
b0000000000001001 *
b0000000000001001 +
#320
b0000 &
b0000000000001010 *
b0000000000001010 +
#321
b0001 &
b0000000000001011 *
b0000000000001011 +
#322
b0010 &
b1111111111111110 *
b1111111111111110 +
#323
b0011 &
b1111111111111111 *
b1111111111111111 +
#324
b0100 &
b0000000000001010 *
b0000000000001010 +
#325
b0101 &
b0000000000010011 *
b0000000000010011 +
#326
b0110 &
b0000000000000110 *
b0000000000000110 +
#327
b0111 &
b0000000000000111 *
b0000000000000111 +
#328
b1000 &
b0000000000001100 *
b0000000000001100 +
#329
b1001 &
b0000000000001101 *
b0000000000001101 +
#330
b1010 &
b0000000000000000 *
b0000000000000000 +
#331
b1011 &
b0000000000000001 *
b0000000000000001 +
#332
b1100 &
b0000000000010100 *
b0000000000010100 +
#333
b1101 &
b0000000000010101 *
b0000000000010101 +
#334
b1110 &
b0000000000001000 *
b0000000000001000 +
#335
b1111 &
b0000000000001001 *
b0000000000001001 +
#336
b0000 &
b0000000000001010 *
b0000000000001010 +
#337
b0001 &
b0000000000001011 *
b0000000000001011 +
#338
b0010 &
b1111111111111110 *
b1111111111111110 +
#339
b0011 &
b1111111111111111 *
b1111111111111111 +
#340
b0100 &
b0000000000001010 *
b0000000000001010 +
#341
b0101 &
b0000000000010011 *
b0000000000010011 +
#342
b0110 &
b0000000000000110 *
b0000000000000110 +
#343
b0111 &
b0000000000000111 *
b0000000000000111 +
#344
b1000 &
b0000000000001100 *
b0000000000001100 +
#345
b1001 &
b0000000000001101 *
b0000000000001101 +
#346
b1010 &
b0000000000000000 *
b0000000000000000 +
#347
b1011 &
b0000000000000001 *
b0000000000000001 +
#348
b1100 &
b0000000000010100 *
b0000000000010100 +
#349
b1101 &
b0000000000010101 *
b0000000000010101 +
#350
b1110 &
b0000000000001000 *
b0000000000001000 +
#351
b1111 &
b0000000000001001 *
b0000000000001001 +
#352
b0000 &
b0000000000001010 *
b0000000000001010 +
#353
b0001 &
b0000000000001011 *
b0000000000001011 +
#354
b0010 &
b1111111111111110 *
b1111111111111110 +
#355
b0011 &
b1111111111111111 *
b1111111111111111 +
#356
b0100 &
b0000000000001010 *
b0000000000001010 +
#357
b0101 &
b0000000000010011 *
b0000000000010011 +
#358
b0110 &
b0000000000000110 *
b0000000000000110 +
#359
b0111 &
b0000000000000111 *
b0000000000000111 +
#360
b1000 &
b0000000000001100 *
b0000000000001100 +
#361
b1001 &
b0000000000001101 *
b0000000000001101 +
#362
b1010 &
b0000000000000000 *
b0000000000000000 +
#363
b1011 &
b0000000000000001 *
b0000000000000001 +
#364
b1100 &
b0000000000010100 *
b0000000000010100 +
#365
b1101 &
b0000000000010101 *
b0000000000010101 +
#366
b1110 &
b0000000000001000 *
b0000000000001000 +
#367
b1111 &
b0000000000001001 *
b0000000000001001 +
#368
b0000 &
b0000000000001010 *
b0000000000001010 +
#369
b0001 &
b0000000000001011 *
b0000000000001011 +
#370
b0010 &
b1111111111111110 *
b1111111111111110 +
#371
b0011 &
b1111111111111111 *
b1111111111111111 +
#372
b0100 &
b0000000000001010 *
b0000000000001010 +
#373
b0101 &
b0000000000010011 *
b0000000000010011 +
#374
b0110 &
b0000000000000110 *
b0000000000000110 +
#375
b0111 &
b0000000000000111 *
b0000000000000111 +
#376
b1000 &
b0000000000001100 *
b0000000000001100 +
#377
b1001 &
b0000000000001101 *
b0000000000001101 +
#378
b1010 &
b0000000000000000 *
b0000000000000000 +
#379
b1011 &
b0000000000000001 *
b0000000000000001 +
#380
b1100 &
b0000000000010100 *
b0000000000010100 +
#381
b1101 &
b0000000000010101 *
b0000000000010101 +
#382
b1110 &
b0000000000001000 *
b0000000000001000 +
#383
b1111 &
b0000000000001001 *
b0000000000001001 +
#384
b0000 &
b0000000000001010 *
b0000000000001010 +
#385
b0001 &
b0000000000001011 *
b0000000000001011 +
#386
b0010 &
b1111111111111110 *
b1111111111111110 +
#387
b0011 &
b1111111111111111 *
b1111111111111111 +
#388
b0100 &
b0000000000001010 *
b0000000000001010 +
#389
b0101 &
b0000000000010011 *
b0000000000010011 +
#390
b0110 &
b0000000000000110 *
b0000000000000110 +
#391
b0111 &
b0000000000000111 *
b0000000000000111 +
#392
b1000 &
b0000000000001100 *
b0000000000001100 +
#393
b1001 &
b0000000000001101 *
b0000000000001101 +
#394
b1010 &
b0000000000000000 *
b0000000000000000 +
#395
b1011 &
b0000000000000001 *
b0000000000000001 +
#396
b1100 &
b0000000000010100 *
b0000000000010100 +
#397
b1101 &
b0000000000010101 *
b0000000000010101 +
#398
b1110 &
b0000000000001000 *
b0000000000001000 +
#399
b1111 &
b0000000000001001 *
b0000000000001001 +
#400
b0000 &
1'
b1111111111110101 *
b1111111111110101 +
#401
b0001 &
b1111111111110100 *
b1111111111110100 +
#402
b0010 &
b0000000000000001 *
b0000000000000001 +
#403
b0011 &
b0000000000000000 *
b0000000000000000 +
#404
b0100 &
b1111111111111101 *
b1111111111111101 +
#405
b0101 &
b1111111111111100 *
b1111111111111100 +
#406
b0110 &
b0000000000001001 *
b0000000000001001 +
#407
b0111 &
b0000000000001000 *
b0000000000001000 +
#408
b1000 &
b1111111111110111 *
b1111111111110111 +
#409
b1001 &
b1111111111110110 *
b1111111111110110 +
#410
b1010 &
b0000000000000011 *
b0000000000000011 +
#411
b1011 &
b0000000000000010 *
b0000000000000010 +
#412
b1100 &
b0000000000000001 *
b0000000000000001 +
#413
b1101 &
b1111111111111110 *
b1111111111111110 +
#414
b1110 &
b0000000000001011 *
b0000000000001011 +
#415
b1111 &
b0000000000001010 *
b0000000000001010 +
#416
b0000 &
b1111111111110101 *
b1111111111110101 +
#417
b0001 &
b1111111111110100 *
b1111111111110100 +
#418
b0010 &
b0000000000000001 *
b0000000000000001 +
#419
b0011 &
b0000000000000000 *
b0000000000000000 +
#420
b0100 &
b1111111111111101 *
b1111111111111101 +
#421
b0101 &
b1111111111111100 *
b1111111111111100 +
#422
b0110 &
b0000000000001001 *
b0000000000001001 +
#423
b0111 &
b0000000000001000 *
b0000000000001000 +
#424
b1000 &
b1111111111110111 *
b1111111111110111 +
#425
b1001 &
b1111111111110110 *
b1111111111110110 +
#426
b1010 &
b0000000000000011 *
b0000000000000011 +
#427
b1011 &
b0000000000000010 *
b0000000000000010 +
#428
b1100 &
b0000000000000001 *
b0000000000000001 +
#429
b1101 &
b1111111111111110 *
b1111111111111110 +
#430
b1110 &
b0000000000001011 *
b0000000000001011 +
#431
b1111 &
b0000000000001010 *
b0000000000001010 +
#432
b0000 &
b1111111111110101 *
b1111111111110101 +
#433
b0001 &
b1111111111110100 *
b1111111111110100 +
#434
b0010 &
b0000000000000001 *
b0000000000000001 +
#435
b0011 &
b0000000000000000 *
b0000000000000000 +
#436
b0100 &
b1111111111111101 *
b1111111111111101 +
#437
b0101 &
b1111111111111100 *
b1111111111111100 +
#438
b0110 &
b0000000000001001 *
b0000000000001001 +
#439
b0111 &
b0000000000001000 *
b0000000000001000 +
#440
b1000 &
b1111111111110111 *
b1111111111110111 +
#441
b1001 &
b1111111111110110 *
b1111111111110110 +
#442
b1010 &
b0000000000000011 *
b0000000000000011 +
#443
b1011 &
b0000000000000010 *
b0000000000000010 +
#444
b1100 &
b0000000000000001 *
b0000000000000001 +
#445
b1101 &
b1111111111111110 *
b1111111111111110 +
#446
b1110 &
b0000000000001011 *
b0000000000001011 +
#447
b1111 &
b0000000000001010 *
b0000000000001010 +
#448
b0000 &
b1111111111110101 *
b1111111111110101 +
#449
b0001 &
b1111111111110100 *
b1111111111110100 +
#450
b0010 &
b0000000000000001 *
b0000000000000001 +
#451
b0011 &
b0000000000000000 *
b0000000000000000 +
#452
b0100 &
b1111111111111101 *
b1111111111111101 +
#453
b0101 &
b1111111111111100 *
b1111111111111100 +
#454
b0110 &
b0000000000001001 *
b0000000000001001 +
#455
b0111 &
b0000000000001000 *
b0000000000001000 +
#456
b1000 &
b1111111111110111 *
b1111111111110111 +
#457
b1001 &
b1111111111110110 *
b1111111111110110 +
#458
b1010 &
b0000000000000011 *
b0000000000000011 +
#459
b1011 &
b0000000000000010 *
b0000000000000010 +
#460
b1100 &
b0000000000000001 *
b0000000000000001 +
#461
b1101 &
b1111111111111110 *
b1111111111111110 +
#462
b1110 &
b0000000000001011 *
b0000000000001011 +
#463
b1111 &
b0000000000001010 *
b0000000000001010 +
#464
b0000 &
b1111111111110101 *
b1111111111110101 +
#465
b0001 &
b1111111111110100 *
b1111111111110100 +
#466
b0010 &
b0000000000000001 *
b0000000000000001 +
#467
b0011 &
b0000000000000000 *
b0000000000000000 +
#468
b0100 &
b1111111111111101 *
b1111111111111101 +
#469
b0101 &
b1111111111111100 *
b1111111111111100 +
