level_3/alu.sv
/****** alu.sv ******/
typedef enum logic [1:0] {
     add     = 2'h1,
     sub     = 2'h2,
     nop     = 2'h0
} operation_t /*verilator public*/;

module alu #(
        parameter WIDTH = 6
) (
        input clk,
        input rst,

        input  operation_t  op_in,
        input  [WIDTH-1:0]  a_in,
        input  [WIDTH-1:0]  b_in,
        input               in_valid,

        output logic [WIDTH-1:0]  out,
        output logic              out_valid
);

        operation_t  op_in_r;
        logic  [WIDTH-1:0]  a_in_r;
        logic  [WIDTH-1:0]  b_in_r;
        logic               in_valid_r;
        logic  [WIDTH-1:0]  result;

        // Register all inputs
        always_ff @ (posedge clk, posedge rst) begin
                if (rst) begin
                        op_in_r     <= nop;   // Use enum value instead of '0
                        a_in_r      <= '0;
                        b_in_r      <= '0;
                        in_valid_r  <= '0;
                end else begin
                        op_in_r    <= op_in;
                        a_in_r     <= a_in;
                        b_in_r     <= b_in;
                        in_valid_r <= in_valid;
                end
        end

        // Compute the result
        always_comb begin
                result = '0;
                if (in_valid_r) begin
                        case (op_in_r)
                                add: result = a_in_r + b_in_r;
                                sub: result = a_in_r + (~b_in_r + 1'b1);
                                default: result = '0;
                        endcase
                end
        end

        // Register outputs
        always_ff @ (posedge clk, posedge rst) begin
                if (rst) begin
                        out       <= '0;
                        out_valid <= '0;
                end else begin
                        out       <= result;
                        out_valid <= in_valid_r;
                end
        end

endmodule

level_3/waveform.vcd
$version Generated by VerilatedVcd $end
$timescale 1ps $end
 $scope module TOP $end
  $var wire 1 ( clk $end
  $var wire 1 ) rst $end
  $var wire 2 * op_in [1:0] $end
  $var wire 6 + a_in [5:0] $end
  $var wire 6 , b_in [5:0] $end
  $var wire 1 - in_valid $end
  $var wire 6 . out [5:0] $end
  $var wire 1 / out_valid $end
  $scope module alu $end
   $var wire 32 0 WIDTH [31:0] $end
   $var wire 1 ( clk $end
   $var wire 1 ) rst $end
   $var wire 2 * op_in [1:0] $end
   $var wire 6 + a_in [5:0] $end
   $var wire 6 , b_in [5:0] $end
   $var wire 1 - in_valid $end
   $var wire 6 . out [5:0] $end
   $var wire 1 / out_valid $end
   $var wire 2 # op_in_r [1:0] $end
   $var wire 6 $ a_in_r [5:0] $end
   $var wire 6 % b_in_r [5:0] $end
   $var wire 1 & in_valid_r $end
   $var wire 6 ' result [5:0] $end
  $upscope $end
 $upscope $end
$enddefinitions $end


#0
b10 #
b111100 $
b011110 %
1&
b011110 '
1(
0)
b10 *
b010011 +
b011100 ,
0-
b010110 .
0/
b00000000000000000000000000000110 0
#1
0(
#2
b010011 $
b011100 %
0&
b000000 '
1(
b011110 .
1/
#3
b00 #
b000000 $
b000000 %
0(
1)
b00 *
b000000 +
b000000 ,
b000000 .
0/
#4
1(
#5
0(
#6
1(
0)
#7
0(
#8
1(
1-
#9
0(
#10
1&
1(
0-
#11
0(
#12
0&
1(
1/
#13
0(
#14
1(
1-
0/
#15
0(
#16
1&
1(
#17
0(
#18
1(
b01 *
b000101 +
b000011 ,
1/
#19
0(
#20
b01 #
b000101 $
b000011 %
b001000 '
1(
0-
#21
0(
#22
0&
b000000 '
1(
b001000 .
#23
0(
#24
1(
b000000 .
0/
#25
0(
#26
1(
#27
0(
#28
1(
#29
0(
#30
1(
#31
0(
#32
1(
#33
0(
#34
1(
#35
0(
#36
1(
1-
#37
0(
#38
1&
b001000 '
1(
b10 *
#39
0(
#40
b10 #
b000010 '
1(
b001000 .
1/
#41
0(
#42
1(
0-
b000010 .
#43
0(
#44
0&
b000000 '
1(
#45
0(
#46
1(
1-
b000000 .
0/
#47
0(
#48
1&
b000010 '
1(
0-
#49
0(
#50
0&
b000000 '
1(
b000010 .
1/
#51
0(
#52
1(
1-
b000000 .
0/
#53
0(
#54
1&
b000010 '
1(
#55
0(
#56
1(
b000010 .
1/
#57
0(
#58
1(
0-
#59
0(
#60
0&
b000000 '
1(
#61
0(
#62
1(
b000000 .
0/
#63
0(
#64
1(
1-
#65
0(
#66
1&
b000010 '
1(
#67
0(
#68
1(
0-
b000010 .
1/
#69
0(
#70
0&
b000000 '
1(
#71
0(
#72
1(
1-
b000000 .
0/
#73
0(
#74
1&
b000010 '
1(
0-
#75
0(
#76
0&
b000000 '
1(
1-
b000010 .
1/
#77
0(
#78
1&
b000010 '
1(
0-
b000000 .
0/
#79
0(
#80
0&
b000000 '
1(
b000010 .
1/
#81
0(
#82
1(
b000000 .
0/
#83
0(
#84
1(
1-
#85
0(
#86
1&
b000010 '
1(
0-
#87
0(
#88
0&
b000000 '
1(
1-
b000010 .
1/
#89
0(
#90
1&
b000010 '
1(
0-
b000000 .
0/
#91
0(
#92
0&
b000000 '
1(
1-
b000010 .
1/
#93
0(
#94
1&
b000010 '
1(
0-
b000000 .
0/
#95
0(
#96
0&
b000000 '
1(
b000010 .
1/
#97
0(
#98
1(
1-
b000000 .
0/
#99
0(
#100
1&
b000010 '
1(
0-
#101
0(
#102
0&
b000000 '
1(
b000010 .
1/
#103
0(
#104
1(
b000000 .
0/
#105
0(
#106
1(
#107
0(
#108
1(
1-
#109
0(
#110
1&
b000010 '
1(
#111
0(
#112
1(
b000010 .
1/
#113
0(
#114
1(
0-
#115
0(
#116
0&
b000000 '
1(
1-
#117
0(
#118
1&
b000010 '
1(
0-
b000000 .
0/
#119
0(
#120
0&
b000000 '
1(
1-
b000010 .
1/
#121
0(
#122
1&
b000010 '
1(
b000000 .
0/
#123
0(
#124
1(
b000010 .
1/
#125
0(
#126
1(
#127
0(
#128
1(
0-
#129
0(
#130
0&
b000000 '
1(
#131
0(
#132
1(
b000000 .
0/
#133
0(
#134
1(
1-
#135
0(
#136
1&
b000010 '
1(
0-
#137
0(
#138
0&
b000000 '
1(
1-
b000010 .
1/
#139
0(
#140
1&
b000010 '
1(
b000000 .
0/
#141
0(
#142
1(
0-
b000010 .
1/
#143
0(
#144
0&
b000000 '
1(
#145
0(
#146
1(
b000000 .
0/
#147
0(
#148
1(
#149
0(
#150
1(
#151
0(
#152
1(
#153
0(
#154
1(
1-
#155
0(
#156
1&
b000010 '
1(
0-
#157
0(
#158
0&
b000000 '
1(
1-
b000010 .
1/
#159
0(
#160
1&
b000010 '
1(
b000000 .
0/
#161
0(
#162
1(
b000010 .
1/
#163
0(
#164
1(
0-
#165
0(
#166
0&
b000000 '
1(
1-
#167
0(
#168
1&
b000010 '
1(
0-
b000000 .
0/
#169
0(
#170
0&
b000000 '
1(
1-
b000010 .
1/
#171
0(
#172
1&
b000010 '
1(
b000000 .
0/
#173
0(
#174
1(
b000010 .
1/
#175
0(
#176
1(
0-
#177
0(
#178
0&
b000000 '
1(
#179
0(
#180
1(
b000000 .
0/
#181
0(
#182
1(
1-
#183
0(
#184
1&
b000010 '
1(
0-
#185
0(
#186
0&
b000000 '
1(
1-
b000010 .
1/
#187
0(
#188
1&
b000010 '
1(
0-
b000000 .
0/
#189
0(
#190
0&
b000000 '
1(
b000010 .
1/
#191
0(
#192
1(
1-
b000000 .
0/
#193
0(
#194
1&
b000010 '
1(
#195
0(
#196
1(
b000010 .
1/
#197
0(
#198
1(
#199
0(
#200
1(
#201
0(
#202
1(
#203
0(
#204
1(
0-
#205
0(
#206
0&
b000000 '
1(
1-
#207
0(
#208
1&
b000010 '
1(
b000000 .
0/
#209
0(
#210
1(
b000010 .
1/
#211
0(
#212
1(
0-
#213
0(
#214
0&
b000000 '
1(
#215
0(
#216
1(
1-
b000000 .
0/
#217
0(
#218
1&
b000010 '
1(
0-
#219
0(
#220
0&
b000000 '
1(
1-
b000010 .
1/
#221
0(
#222
1&
b000010 '
1(
0-
b000000 .
0/
#223
0(
#224
0&
b000000 '
1(
b000010 .
1/
#225
0(
#226
1(
b000000 .
0/
#227
0(
#228
1(
1-
#229
0(
#230
1&
b000010 '
1(
0-
#231
0(
#232
0&
b000000 '
1(
b000010 .
1/
#233
0(
#234
1(
b000000 .
0/
#235
0(
#236
1(
#237
0(
#238
1(
1-
#239
0(
#240
1&
b000010 '
1(
0-
#241
0(
#242
0&
b000000 '
1(
1-
b000010 .
1/
#243
0(
#244
1&
b000010 '
1(
b000000 .
0/
#245
0(
#246
1(
b000010 .
1/
#247
0(
#248
1(
#249
0(
#250
1(
#251
0(
#252
1(
#253
0(
#254
1(
#255
0(
#256
1(
0-
#257
0(
#258
0&
b000000 '
1(
#259
0(
#260
1(
1-
b000000 .
0/
#261
0(
#262
1&
b000010 '
1(
#263
0(
#264
1(
b000010 .
1/
#265
0(
#266
1(
#267
0(
#268
1(
#269
0(
#270
1(
0-
#271
0(
#272
0&
b000000 '
1(
#273
0(
#274
1(
1-
b000000 .
0/
#275
0(
#276
1&
b000010 '
1(
0-
#277
0(
#278
0&
b000000 '
1(
b000010 .
1/
#279
0(
#280
1(
1-
b000000 .
0/
#281
0(
#282
1&
b000010 '
1(
#283
0(
#284
1(
b000010 .
1/
#285
0(
#286
1(
#287
0(
#288
1(
#289
0(
#290
1(
0-
#291
0(
#292
0&
b000000 '
1(
#293
0(
#294
1(
1-
b000000 .
0/
#295
0(
#296
1&
b000010 '
1(
#297
0(
#298
1(
b000010 .
1/
